{ 
"titulo": "Computadoras de ultima generación",

"codigo ": "325436eg",

"subcategoria" : "424656245",

"informacion" : {
    "marca":"HP",
    "serie" : "2345DHSFGHS",
    "colorstandar" : "verde",
    "peso" : "24kg",
    "volumen" : "123 m3",
    "stock" : "234"


},

"variantes" : {
         "existe" : true,
         "color" : ["Verde", "Azul" ]
        },

"imgs" : {
        "principal": "153451545"

        },

"descripcion" : "Producto muy bueno para comprarlo este veradmp",

"etiquetas" : {
    "primero": "es muy bueno",
    "segundo": " Velox"

}

}